{"charge":{"duplicated":false,"object":"charge","id":"chr_test_OdJvefU8erMhhtBe","creation_date":1534103794000,"amount":19500,"amount_refunded":0,"current_amount":19500,"installments":0,"installments_amount":null,"currency_code":"PEN","email":"will2@will.com","description":null,"source":{"object":"token","id":"tkn_test_L6sXCgoMPGbNm1UT","type":"card","creation_date":1534103788000,"email":"will2@will.com","card_number":"411111******1111","last_four":"1111","active":true,"iin":{"object":"iin","bin":"411111","card_brand":"Visa","card_type":"credito","card_category":"Cl\u00e1sica","issuer":{"name":"BBVA","country":"PERU","country_code":"PE","website":null,"phone_number":null},"installments_allowed":[2,4,6,8,10,12,3,5,7,9,24,48]},"client":{"ip":"200.106.118.192","ip_country":"Per\u00fa","ip_country_code":"PE","browser":null,"device_fingerprint":"1404278125","device_type":"Escritorio"},"metadata":{"method":"checkout","client_ip":"200.106.118.192","secure":"false","url":"http:\/\/commerce.dd:8083\/checkout\/42\/payment"}},"outcome":{"type":"venta_exitosa","code":"AUT0000","merchant_message":"La operaci\u00f3n de venta ha sido autorizada exitosamente","user_message":"Su compra ha sido exitosa."},"fraud_score":9,"dispute":false,"capture":true,"reference_code":"vFLk3YUm61","authorization_code":"efYsBz","metadata":{},"total_fee":863,"fee_details":{"fixed_fee":{},"variable_fee":{"currency_code":"PEN","commision":0.037499999999999999,"total":731}},"total_fee_taxes":132,"transfer_amount":18637,"paid":false,"statement_descriptor":"CULQI*","transfer_id":null}}